<Properties StartupConfiguration="{CC0E676E-C381-4B1D-A457-205D049B95C6}|https">
  <MonoDevelop.Ide.Workbench ActiveDocument="DAO/Database.cs">
    <Files>
      <File FileName="Models/Group.cs" Line="9" Column="13" />
      <File FileName="DAO/Database.cs" Line="146" Column="1" />
      <File FileName="Program.cs" Line="22" Column="43" />
      <File FileName="Controllers/HomeController.cs" Line="103" Column="25" />
      <File FileName="Controllers/ResponseController.cs" Line="38" Column="14" />
      <File FileName="Models/Response.cs" Line="25" Column="10" />
    </Files>
    <Pads>
      <Pad Id="ProjectPad">
        <State name="__root__">
          <Node name="WebExtension" expanded="True">
            <Node name="WebExtension" expanded="True">
              <Node name="Controllers" expanded="True" />
              <Node name="DAO" expanded="True">
                <Node name="Database.cs" selected="True" />
              </Node>
              <Node name="Models" expanded="True" />
              <Node name="Properties" expanded="True" />
            </Node>
          </Node>
        </State>
      </Pad>
    </Pads>
  </MonoDevelop.Ide.Workbench>
  <MultiItemStartupConfigurations />
  <MonoDevelop.Ide.ItemProperties.WebExtension PreferredExecutionTarget="/Applications/Google Chrome.app" />
  <MonoDevelop.Ide.DebuggingService.Breakpoints>
    <BreakpointStore />
  </MonoDevelop.Ide.DebuggingService.Breakpoints>
  <MonoDevelop.Ide.Workspace ActiveConfiguration="Debug" />
  <MonoDevelop.Ide.DebuggingService.PinnedWatches />
</Properties>